{"4":{"week":1},"Did":{"you":1},"you":{"hear":0.8,"call":0.2},"hear":{"about":0.7,"the":0.1,"high":0.1,"a":0.1},"about":{"the":0.7272727272727273,"?":0.09090909090909091,"their":0.09090909090909091,"being":0.09090909090909091},"the":{"guy":0.05,"skeleton":0.05,"road":0.05,"stadium":0.05,"game":0.05,"dark":0.05,"tomato":0.05,"joke":0.05,"wandering":0.05,"kid":0.05,"playground":0.05,"winter":0.05,"ability":0.05,"cheese":0.05,"runner":0.05,"submarine":0.05,"chameleon":0.05,"scientist":0.05,"Mexican":0.05,"worst":0.05},"guy":{"whose":1},"whose":{"whole":1},"whole":{"left":1},"left":{"side":1},"side":{"was":1},"was":{"cut":0.25,"it":0.25,"criticized":0.25,"lab":0.25},"cut":{"off":1},"off":{"?":1},"Why":{"didnundefinedt":0.16666666666666666,"was":0.16666666666666666,"did":0.3333333333333333,"do":0.16666666666666666,"does":0.16666666666666666},"didnundefinedt":{"the":1},"skeleton":{"cross":1},"cross":{"the":1},"road":{"?":1},"What":{"did":0.16666666666666666,"creature":0.16666666666666666,"is":0.3333333333333333,"do":0.3333333333333333},"did":{"one":0.3333333333333333,"the":0.6666666666666666},"one":{"nut":1},"nut":{"say":0.5,"?":0.5},"say":{"as":1},"as":{"he":0.5,"they":0.5},"he":{"chased":1},"chased":{"another":1},"another":{"nut":1},"How":{"come":0.5,"many":0.5},"come":{"the":1},"stadium":{"got":1},"got":{"hot":1},"hot":{"after":1},"after":{"the":1},"game":{"?":1},"it":{"called":0.5,"take":0.5},"called":{"the":1},"dark":{"ages":1},"ages":{"?":1},"tomato":{"blush":1},"blush":{"?":1},"joke":{"about":1},"wandering":{"nun":1},"nun":{"?":1},"creature":{"is":1},"is":{"smarter":0.3333333333333333,"a":0.3333333333333333,"this":0.3333333333333333},"smarter":{"than":1},"than":{"a":0.5,"an":0.5},"a":{"talking":0.1,"centipedes's":0.1,"Moon-rock":0.1,"lightbulb":0.1,"dog":0.1,"fashionable":0.1,"crowd":0.1,"hotel":0.1,"pot":0.1,"cross-eyed":0.1},"talking":{"parrot":1},"parrot":{"?":1},"kid":{"cross":1},"playground":{"?":1},"do":{"birds":0.2,"you":0.4,"we":0.2,"now":0.2},"birds":{"fly":1},"fly":{"south":1},"south":{"for":1},"for":{"the":1},"winter":{"?":1},"centipedes's":{"favorite":1},"favorite":{"Beatle":1},"Beatle":{"song":1},"song":{"?":1},"does":{"a":0.5,"it":0.5},"Moon-rock":{"taste":1},"taste":{"better":1},"better":{"than":1},"an":{"Earth-rock":0.5,"excellent":0.5},"Earth-rock":{"?":1},"many":{"kids":1},"kids":{"with":1},"with":{"ADD":0.3333333333333333,"an":0.3333333333333333,"a":0.3333333333333333},"ADD":{"does":1},"take":{"to":1},"to":{"change":0.5,"hear":0.5},"change":{"a":0.5,"color":0.5},"lightbulb":{"?":1},"Meundefined":{"If":1},"If":{"humans":1},"humans":{"lose":1},"lose":{"the":1},"ability":{"to":1},"high":{"frequency":1},"frequency":{"volumes":1},"volumes":{"as":1},"they":{"get":1},"get":{"olderundefined":1},"olderundefined":{"can":1},"can":{"my":1},"my":{"4":1},"week":{"old":1},"old":{"son":1},"son":{"hear":1},"dog":{"whistle":1},"whistle":{"?":1},"call":{"a":1},"fashionable":{"lawn":1},"lawn":{"statue":1},"statue":{"with":1},"excellent":{"sense":1},"sense":{"of":1},"of":{"rhythmn":0.3333333333333333,"chess":0.3333333333333333,"boiling":0.3333333333333333},"rhythmn":{"?":1},"Wifeundefined":{"Honey":1},"Honey":{"Iundefinedm":1},"Iundefinedm":{"pregnantundefinedundefinedundefinedundefinedundefinedMeundefined":1},"pregnantundefinedundefinedundefinedundefinedundefinedMeundefined":{"Wellundefinedundefined":1},"Wellundefinedundefined":{"what":1},"what":{"do":1},"we":{"do":1},"now":{"?":1},"cheese":{"factory":1},"factory":{"that":1},"that":{"exploded":1},"exploded":{"in":1},"in":{"France":0.5,"a":0.5},"France":{"?":1},"runner":{"who":1},"who":{"was":0.6666666666666666,"couldn't":0.3333333333333333},"criticized":{"?":1},"this":{"movie":1},"movie":{"about":1},"submarine":{"industry":1},"industry":{"?":1},"crowd":{"of":1},"chess":{"players":1},"players":{"bragging":1},"bragging":{"about":1},"their":{"wins":1},"wins":{"in":1},"hotel":{"lobby":1},"lobby":{"?":1},"chameleon":{"who":1},"couldn't":{"change":1},"color":{"?":1},"scientist":{"who":1},"lab":{"partners":1},"partners":{"with":1},"pot":{"of":1},"boiling":{"water":1},"water":{"?":1},"Mexican":{"train":1},"train":{"killer":1},"killer":{"?":1},"What's":{"the":1},"worst":{"part":1},"part":{"about":1},"being":{"a":1},"cross-eyed":{"teacher":1},"teacher":{"?":1}}