[{"_id":"5ca685aa67d65a48fd540840","id":"0189hNRf2g","joke":"I'm tired of following my dreams. I'm just going to ask them where they are going and meet up with them later.","__v":0},{"_id":"5ca685aa67d65a48fd540841","id":"08EQZ8EQukb","joke":"Did you hear about the guy whose whole left side was cut off? He's all right now.","__v":0},{"_id":"5ca685aa67d65a48fd540842","id":"08xHQCdx5Ed","joke":"Why didn’t the skeleton cross the road? Because he had no guts.","__v":0},{"_id":"5ca685aa67d65a48fd540843","id":"0DQKB51oGlb","joke":"What did one nut say as he chased another nut?  I'm a cashew!","__v":0},{"_id":"5ca685aa67d65a48fd540844","id":"0LuXvkq4Muc","joke":"I knew I shouldn't steal a mixer from work, but it was a whisk I was willing to take.","__v":0},{"_id":"5ca685aa67d65a48fd540845","id":"0ga2EdN7prc","joke":"How come the stadium got hot after the game? Because all of the fans left.","__v":0},{"_id":"5ca685aa67d65a48fd540846","id":"0oO71TSv4Ed","joke":"Why was it called the dark ages? Because of all the knights. ","__v":0},{"_id":"5ca685aa67d65a48fd540847","id":"0oz51ozk3ob","joke":"A steak pun is a rare medium well done.","__v":0},{"_id":"5ca685aa67d65a48fd540848","id":"0ozAXv4Mmjb","joke":"Why did the tomato blush? Because it saw the salad dressing.","__v":0},{"_id":"5ca685aa67d65a48fd540849","id":"0wcFBQfiGBd","joke":"Did you hear the joke about the wandering nun? She was a roman catholic.","__v":0},{"_id":"5ca685aa67d65a48fd54084a","id":"189xHQ7pOuc","joke":"What creature is smarter than a talking parrot? A spelling bee.","__v":0},{"_id":"5ca685aa67d65a48fd54084b","id":"18Elj3EIYvc","joke":"I'll tell you what often gets over looked; garden fences.","__v":0},{"_id":"5ca685aa67d65a48fd54084c","id":"18h3wcU8xAd","joke":"Why did the kid cross the playground? To get to the other slide.","__v":0},{"_id":"5ca685aa67d65a48fd54084d","id":"1DIRSfx51Dd","joke":"Why do birds fly south for the winter? Because it's too far to walk.","__v":0},{"_id":"5ca685aa67d65a48fd54084e","id":"1DQZDY0gVnb","joke":"What is a centipedes's favorite Beatle song?  I want to hold your hand, hand, hand, hand;","__v":0},{"_id":"5ca685aa67d65a48fd54084f","id":"1DQZvXvX8Ed","joke":"My first time using an elevator was an uplifting experience. The second time let me down.","__v":0},{"_id":"5ca685aa67d65a48fd540850","id":"1DQZvcFBdib","joke":"To be Frank, I'd have to change my name.","__v":0},{"_id":"5ca685aa67d65a48fd540851","id":"1Dt4M7Ufaxc","joke":"Slept like a log last night ; woke up in the fireplace.","__v":0},{"_id":"5ca685aa67d65a48fd540852","id":"1T01LBXLuzd","joke":"Why does a Moon-rock taste better than an Earth-rock? Because it's a little meteor.","__v":0},{"_id":"5ca685aa67d65a48fd540853","id":"1T0gqOZT0g","joke":"I thought my wife was joking when she said she'd leave me if I didn't stop signing \"I'm A Believer\"; Then I saw her face.","__v":0},{"_id":"5ca6890545c4db4f01359f57","id":"HtcNuHJBQCd","joke":"How many kids with ADD does it take to change a lightbulb? Let's go ride bikes!","__v":0},{"_id":"5ca6891ed9e1984f4c5dd5b1","id":"82wHlbaapzd","joke":"Me: If humans lose the ability to hear high frequency volumes as they get older, can my 4 week old son hear a dog whistle?\r\n\r\nDoctor: No, humans can never hear that high of a frequency no matter what age they are.\r\n\r\nMe: Trick question; dogs can't whistle.","__v":0},{"_id":"5ca6891ed9e1984f4c5dd5b2","id":"Tvcah31oWvc","joke":"What do you call a fashionable lawn statue with an excellent sense of rhythmn? A metro-gnome","__v":0},{"_id":"5ca6891ed9e1984f4c5dd5b3","id":"i39hqWnGljb","joke":"When Dad drops a pea off of his plate ‘oh dear I’ve pee’d on the table!","__v":0},{"_id":"5ca6891ed9e1984f4c5dd5b4","id":"nWvXSvHBd","joke":"I hate perforated lines, they're tearable.","__v":0},{"_id":"5ca6891ed9e1984f4c5dd5b5","id":"UfqHY8EQClb","joke":"I wear a stethoscope so that in a medical emergency I can teach people a valuable lesson about assumptions.","__v":0},{"_id":"5ca6891ed9e1984f4c5dd5b6","id":"7h3oGtrOfxc","joke":"Whiteboards ; are remarkable.","__v":0},{"_id":"5ca6891ed9e1984f4c5dd5b7","id":"29ElG6p49pb","joke":"Wife: Honey I’m pregnant.\r\n\r\nMe: Well;. what do we do now?\r\n\r\nWife: Well, I guess we should go to a baby doctor.\r\n\r\nMe: Hm. I think I’d be a lot more comfortable going to an adult doctor.","__v":0},{"_id":"5ca6891fd9e1984f4c5dd5b8","id":"nWDdFdFYLuc","joke":"Have you heard about the film \"Constipation\", you probably haven't because it's not out yet.","__v":0},{"_id":"5ca6891fd9e1984f4c5dd5b9","id":"SSCQCdi39Ed","joke":"Did you hear about the cheese factory that exploded in France? There was nothing left but de Brie.","__v":0},{"_id":"5ca6891fd9e1984f4c5dd5ba","id":"vkV0L6wcFlb","joke":"Did you hear about the runner who was criticized? He just took it in stride","__v":0},{"_id":"5ca6891fd9e1984f4c5dd5bb","id":"Sn39Elb2LBd","joke":"What is this movie about? It is about 2 hours long.","__v":0},{"_id":"5ca6891fd9e1984f4c5dd5bc","id":"s4Me29U0gqc","joke":"Cosmetic surgery used to be such a taboo subject.\r\nNow you can talk about Botox and nobody raises an eyebrow.","__v":0},{"_id":"5ca6891fd9e1984f4c5dd5bd","id":"eiiVvH6MCd","joke":"Did you hear about the submarine industry? It really took a dive;","__v":0},{"_id":"5ca6891fd9e1984f4c5dd5be","id":"ahqjV82LBAd","joke":"I was thinking about moving to Moscow but there is no point Russian into things.","__v":0},{"_id":"5ca6891fd9e1984f4c5dd5bf","id":"K6USKBXvcib","joke":"What do you call a crowd of chess players bragging about their wins in a hotel lobby? Chess nuts boasting in an open foyer.","__v":0},{"_id":"5ca6891fd9e1984f4c5dd5c0","id":"99U0T7hVDlb","joke":"Just read a few facts about frogs. They were ribbiting.","__v":0},{"_id":"5ca6891fd9e1984f4c5dd5c1","id":"f211DdFBdxc","joke":"Did you hear about the chameleon who couldn't change color? They had a reptile dysfunction.","__v":0},{"_id":"5ca6891fd9e1984f4c5dd5c2","id":"kqcFBlGJYDd","joke":"You know what they say about cliffhangers;","__v":0},{"_id":"5ca6891fd9e1984f4c5dd5c3","id":"scaUn3TfNe","joke":"So, I heard this pun about cows, but it’s kinda offensive so I won’t say it. I don’t want there to be any beef between us. ","__v":0},{"_id":"5ca6891fd9e1984f4c5dd5c4","id":"KJmW8h3oWnb","joke":"Did you hear about the scientist who was lab partners with a pot of boiling water? He had a very esteemed colleague.","__v":0},{"_id":"5ca6891fd9e1984f4c5dd5c6","id":"6MZobUfVKuc","joke":"I just read a book about Stockholm syndrome. It was pretty bad at first, but by the end I liked it.","__v":0},{"_id":"5ca6891fd9e1984f4c5dd5c5","id":"ozPmbFtWDlb","joke":"Some people say that comedians who tell one too many light bulb jokes soon burn out, but they don't know watt they are talking about. They're not that bright.","__v":0},{"_id":"5ca6891fd9e1984f4c5dd5c7","id":"Xn3wX8hi3Ed","joke":"Did you hear about the Mexican train killer? He had loco motives","__v":0},{"_id":"5ca6891fd9e1984f4c5dd5c8","id":"TvPfV8prOuc","joke":"What's the worst part about being a cross-eyed teacher?\r\n\r\nThey can't control their pupils.","__v":0},{"_id":"5ca6891fd9e1984f4c5dd5c9","id":"gNZTCQnWSf","joke":"The other day I was listening to a song about superglue, it’s been stuck in my head ever since.","__v":0}]